{
  "schemaVersion": 1,
  "dataVersion": "cf8a5200d2088aa0",
  "category": {
    "id": "minced-crisp",
    "name": "鬆",
    "keywords": [
      "鬆"
    ],
    "videoCount": 18,
    "dataPath": "categories/minced-crisp.json"
  },
  "videos": [
    {
      "id": "minced-crisp-0001-4v7GFy5mclY",
      "title": "傅培梅時間-雙味蝦鬆",
      "url": "https://www.youtube.com/watch?v=4v7GFy5mclY",
      "videoId": "4v7GFy5mclY",
      "embedUrl": "https://www.youtube-nocookie.com/embed/4v7GFy5mclY",
      "categoryId": "minced-crisp",
      "categoryName": "鬆"
    },
    {
      "id": "minced-crisp-0002-j69VlBT_st8",
      "title": "傅培梅時間 -鴛鴦蝦鬆",
      "url": "https://www.youtube.com/watch?v=j69VlBT_st8",
      "videoId": "j69VlBT_st8",
      "embedUrl": "https://www.youtube-nocookie.com/embed/j69VlBT_st8",
      "categoryId": "minced-crisp",
      "categoryName": "鬆"
    },
    {
      "id": "minced-crisp-0003-I2J5Uxh80PU",
      "title": "傅培梅時間-生菜田雞鬆",
      "url": "https://www.youtube.com/watch?v=I2J5Uxh80PU",
      "videoId": "I2J5Uxh80PU",
      "embedUrl": "https://www.youtube-nocookie.com/embed/I2J5Uxh80PU",
      "categoryId": "minced-crisp",
      "categoryName": "鬆"
    },
    {
      "id": "minced-crisp-0004-q3L3YCqicpU",
      "title": "【在家輕鬆煮】咖哩炒泡麵",
      "url": "https://www.youtube.com/watch?v=q3L3YCqicpU",
      "videoId": "q3L3YCqicpU",
      "embedUrl": "https://www.youtube-nocookie.com/embed/q3L3YCqicpU",
      "categoryId": "minced-crisp",
      "categoryName": "鬆"
    },
    {
      "id": "minced-crisp-0005-cARL9EDOfB0",
      "title": "傅培梅時間 - 生菜蝦鬆",
      "url": "https://www.youtube.com/watch?v=cARL9EDOfB0",
      "videoId": "cARL9EDOfB0",
      "embedUrl": "https://www.youtube-nocookie.com/embed/cARL9EDOfB0",
      "categoryId": "minced-crisp",
      "categoryName": "鬆"
    },
    {
      "id": "minced-crisp-0006-l1tuSqsvR4k",
      "title": "傅培梅時間 - 生菜鴿鬆",
      "url": "https://www.youtube.com/watch?v=l1tuSqsvR4k",
      "videoId": "l1tuSqsvR4k",
      "embedUrl": "https://www.youtube-nocookie.com/embed/l1tuSqsvR4k",
      "categoryId": "minced-crisp",
      "categoryName": "鬆"
    },
    {
      "id": "minced-crisp-0007-t591cSRInec",
      "title": "傅培梅時間 -生炒牛肉鬆",
      "url": "https://www.youtube.com/watch?v=t591cSRInec",
      "videoId": "t591cSRInec",
      "embedUrl": "https://www.youtube-nocookie.com/embed/t591cSRInec",
      "categoryId": "minced-crisp",
      "categoryName": "鬆"
    },
    {
      "id": "minced-crisp-0008-6fG_0rqnrNM",
      "title": "【在家輕鬆煮】簡易版香菇肉燥",
      "url": "https://www.youtube.com/watch?v=6fG_0rqnrNM",
      "videoId": "6fG_0rqnrNM",
      "embedUrl": "https://www.youtube-nocookie.com/embed/6fG_0rqnrNM",
      "categoryId": "minced-crisp",
      "categoryName": "鬆"
    },
    {
      "id": "minced-crisp-0009-Woci1gW7uLE",
      "title": "傅培梅時間-生炒蝦鬆.麻辣海蔘",
      "url": "https://www.youtube.com/watch?v=Woci1gW7uLE",
      "videoId": "Woci1gW7uLE",
      "embedUrl": "https://www.youtube-nocookie.com/embed/Woci1gW7uLE",
      "categoryId": "minced-crisp",
      "categoryName": "鬆"
    },
    {
      "id": "minced-crisp-0010-pEd2k2v82oE",
      "title": "傅培梅時間-韭黃雞鬆.松仁雞丁",
      "url": "https://www.youtube.com/watch?v=pEd2k2v82oE",
      "videoId": "pEd2k2v82oE",
      "embedUrl": "https://www.youtube-nocookie.com/embed/pEd2k2v82oE",
      "categoryId": "minced-crisp",
      "categoryName": "鬆"
    },
    {
      "id": "minced-crisp-0011-AbIv1OREcCk",
      "title": "傅培梅時間-金盤蝦鬆.豉汁焗蝦碌",
      "url": "https://www.youtube.com/watch?v=AbIv1OREcCk",
      "videoId": "AbIv1OREcCk",
      "embedUrl": "https://www.youtube-nocookie.com/embed/AbIv1OREcCk",
      "categoryId": "minced-crisp",
      "categoryName": "鬆"
    },
    {
      "id": "minced-crisp-0012-VleZkZONwME",
      "title": "傅培梅時間-生菜田雞鬆.釀百花素雞",
      "url": "https://www.youtube.com/watch?v=VleZkZONwME",
      "videoId": "VleZkZONwME",
      "embedUrl": "https://www.youtube-nocookie.com/embed/VleZkZONwME",
      "categoryId": "minced-crisp",
      "categoryName": "鬆"
    },
    {
      "id": "minced-crisp-0013-p4aLVN1iWJI",
      "title": "傅培梅時間-生菜鮮肉鬆.肉醬烤麵皮",
      "url": "https://www.youtube.com/watch?v=p4aLVN1iWJI",
      "videoId": "p4aLVN1iWJI",
      "embedUrl": "https://www.youtube-nocookie.com/embed/p4aLVN1iWJI",
      "categoryId": "minced-crisp",
      "categoryName": "鬆"
    },
    {
      "id": "minced-crisp-0014-2oLlzZ1CHKM",
      "title": "傅培梅時間-蛋鬆飯.蛋包飯.親子丼",
      "url": "https://www.youtube.com/watch?v=2oLlzZ1CHKM",
      "videoId": "2oLlzZ1CHKM",
      "embedUrl": "https://www.youtube-nocookie.com/embed/2oLlzZ1CHKM",
      "categoryId": "minced-crisp",
      "categoryName": "鬆"
    },
    {
      "id": "minced-crisp-0015-UEcCW3sypb0",
      "title": "傅培梅時間-天天好市(蠔鬆).發財如意(素羹)",
      "url": "https://www.youtube.com/watch?v=UEcCW3sypb0",
      "videoId": "UEcCW3sypb0",
      "embedUrl": "https://www.youtube-nocookie.com/embed/UEcCW3sypb0",
      "categoryId": "minced-crisp",
      "categoryName": "鬆"
    },
    {
      "id": "minced-crisp-0016-4uODhVgpeMU",
      "title": "早餐別出去買，5個雞蛋，一碗麵粉，香甜鬆軟還拉絲，比麵包片好吃多了！ 【洪洋美食日記】",
      "url": "https://www.youtube.com/watch?v=4uODhVgpeMU",
      "videoId": "4uODhVgpeMU",
      "embedUrl": "https://www.youtube-nocookie.com/embed/4uODhVgpeMU",
      "categoryId": "minced-crisp",
      "categoryName": "鬆"
    },
    {
      "id": "minced-crisp-0017-9_b3zmF4OVg",
      "title": "Vita Dolce甜蜜生活手作甜點》斑馬紋切開超美！在家跟著做輕鬆升級戚風蛋糕《VS MEDIA》",
      "url": "https://www.youtube.com/watch?v=9_b3zmF4OVg",
      "videoId": "9_b3zmF4OVg",
      "embedUrl": "https://www.youtube-nocookie.com/embed/9_b3zmF4OVg",
      "categoryId": "minced-crisp",
      "categoryName": "鬆"
    },
    {
      "id": "minced-crisp-0018-ZHd2536DfvY",
      "title": "舒芙蕾鬆餅的做法 只需4種材料 免烤箱  2種口味一次分享 SOUFFLÉ PANCAKE RECIPE ｜乾杯與小菜的日常",
      "url": "https://www.youtube.com/watch?v=ZHd2536DfvY",
      "videoId": "ZHd2536DfvY",
      "embedUrl": "https://www.youtube-nocookie.com/embed/ZHd2536DfvY",
      "categoryId": "minced-crisp",
      "categoryName": "鬆"
    }
  ]
}
